pydoc_markdown_nuxt/__init__.py
pydoc_markdown_nuxt/renderer.py
pydoc_markdown_nuxt-0.2.1.dist-info/licenses/LICENSE
pydoc_markdown_nuxt-0.2.1.dist-info/METADATA
pydoc_markdown_nuxt-0.2.1.dist-info/WHEEL
pydoc_markdown_nuxt-0.2.1.dist-info/entry_points.txt
pydoc_markdown_nuxt-0.2.1.dist-info/top_level.txt
pydoc_markdown_nuxt-0.2.1.dist-info/RECORD
