Metadata-Version: 2.4
Name: pydoc-markdown-nuxt
Version: 0.2.1
Summary: A Nuxt.js renderer for pydoc-markdown that generates documentation compatible with Nuxt Content and MDC
Author-email: Uriel Curiel <kratoz.00616@gmail.com>
License: MIT License
Keywords: pydoc-markdown,nuxt,documentation,python,mdc,nuxt-content
Classifier: Development Status :: 3 - Alpha
Classifier: Intended Audience :: Developers
Classifier: License :: OSI Approved :: MIT License
Classifier: Programming Language :: Python :: 3
Classifier: Programming Language :: Python :: 3.8
Classifier: Programming Language :: Python :: 3.9
Classifier: Programming Language :: Python :: 3.10
Classifier: Programming Language :: Python :: 3.11
Classifier: Programming Language :: Python :: 3.12
Classifier: Topic :: Documentation
Classifier: Topic :: Software Development :: Documentation
Requires-Python: >=3.8
License-File: LICENSE
Requires-Dist: build>=1.2.2.post1
Requires-Dist: pydoc-markdown>=4.8.2
Requires-Dist: pytest>=8.3.5
Requires-Dist: pytest-cov>=5.0.0
Requires-Dist: PyYAML>=5.0
Requires-Dist: twine>=6.1.0
Provides-Extra: dev
Requires-Dist: pytest>=7.0.0; extra == "dev"
Requires-Dist: pytest-cov>=4.1.0; extra == "dev"
Dynamic: license-file
